tarvis/exchange/binance/__init__.py
tarvis_exchange_binance-0.9.11.dist-info/LICENSE.txt
tarvis_exchange_binance-0.9.11.dist-info/METADATA
tarvis_exchange_binance-0.9.11.dist-info/WHEEL
tarvis_exchange_binance-0.9.11.dist-info/top_level.txt
tarvis_exchange_binance-0.9.11.dist-info/RECORD
