Metadata-Version: 2.1
Name: tarvis-exchange-binance
Version: 0.9.11
Summary: Tarvis Exchange Library for Binance
Home-page: https://tarvislabs.com/
Author: Tarvis Labs
Author-email: python@tarvislabs.com
License: MIT
Platform: UNKNOWN
Classifier: License :: OSI Approved :: MIT License
Requires-Python: >=3.10
License-File: LICENSE.txt
Requires-Dist: binance-connector (==2.0.0)
Requires-Dist: binance-futures-connector (==3.3.1)
Requires-Dist: requests (==2.28.1)
Requires-Dist: tarvis-common (==0.9.11)
